[{"id":6,"name":6,"address":"\uacbd\uae30\ub3c4 \uc758\uc815\ubd80\uc2dc \uc2e0\ud765\ub85c 194","delivery_status":false,"index_x":"37.7334273","index_y":"127.043799","cluster_num":42},{"id":7,"name":7,"address":"\uacbd\uae30\ub3c4 \uc758\uc815\ubd80\uc2dc \uc2e0\ud765\ub85c 196 \ub3c4\ub9bc\ube4c\ub529","delivery_status":false,"index_x":"37.7336021","index_y":"127.0437888","cluster_num":42},{"id":8,"name":8,"address":"\uacbd\uae30\ub3c4 \uc758\uc815\ubd80\uc2dc \uc2e0\ud765\ub85c 192 \ud558\ub098\ube4c\ub529","delivery_status":false,"index_x":"37.7332587","index_y":"127.0438136","cluster_num":42}]