[{"id":24,"name":24,"address":"경기도 의정부시 신흥로232번길 11","delivery_status":false,"index_x":"37.7369642","index_y":"127.0441705","cluster_num":4},{"id":25,"name":25,"address":"경기도 의정부시 신흥로232번길 11","delivery_status":false,"index_x":"37.7369685","index_y":"127.0440939","cluster_num":4},{"id":26,"name":26,"address":"경기도 의정부시 신흥로232번길 11","delivery_status":false,"index_x":"37.7369642","index_y":"127.0441705","cluster_num":4},{"id":27,"name":27,"address":"경기도 의정부시 신흥로232번길 5","delivery_status":false,"index_x":"37.7369563","index_y":"127.0439413","cluster_num":4},{"id":29,"name":29,"address":"경기도 의정부시 신흥로232번길 11","delivery_status":false,"index_x":"37.7369642","index_y":"127.0441705","cluster_num":4},{"id":30,"name":30,"address":"경기도 의정부시 신흥로232번길 5","delivery_status":false,"index_x":"37.7369563","index_y":"127.0439413","cluster_num":4}]